tesedml-0.4.5.3.data/purelib/tesedml/__init__.py
tesedml-0.4.5.3.data/purelib/tesedml/_libsedml.so
tesedml-0.4.5.3.data/purelib/tesedml/libsedml.py
tesedml-0.4.5.3.dist-info/METADATA
tesedml-0.4.5.3.dist-info/WHEEL
tesedml-0.4.5.3.dist-info/top_level.txt
tesedml-0.4.5.3.dist-info/RECORD
