Metadata-Version: 2.1
Name: tesedml
Version: 0.4.5.3
Summary: LibSEDML Python API
Home-page: http://sed-ml.org/
Author: Frank T. Bergmann, J Kyle Medley (packaging)
Author-email: UNKNOWN
License: LGPL
Platform: UNKNOWN
Classifier: Intended Audience :: Science/Research
Classifier: Operating System :: MacOS :: MacOS X
Classifier: Operating System :: Microsoft :: Windows
Classifier: Operating System :: POSIX
Classifier: Programming Language :: C++
